.travis.yml
README.rst
propdict.py
setup.py
test_propdict.py
tox.ini
propdict.egg-info/PKG-INFO
propdict.egg-info/SOURCES.txt
propdict.egg-info/dependency_links.txt
propdict.egg-info/not-zip-safe
propdict.egg-info/requires.txt
propdict.egg-info/top_level.txt