Metadata-Version: 1.1
Name: propdict
Version: 1.1
Summary: A Python dictionary implementation that supports properties, class variables and inheritance for your sophisticated templating needs.
Home-page: https://github.com/tomster/propdict
Author: Tom Lazar
Author-email: tom@tomster.org
License: BSD
Platform: UNKNOWN
Classifier: Development Status :: 5 - Production/Stable
Classifier: License :: OSI Approved :: BSD License
Classifier: Intended Audience :: Developers
Classifier: License :: OSI Approved :: BSD License
Classifier: Programming Language :: Python :: 2.6
Classifier: Programming Language :: Python :: 2.7
Classifier: Programming Language :: Python :: 3.3
